revus/__init__.py
revus/app/__init__.py
revus/app/cli.py
revus/app/code_reviewer.py
revus/app/config.py
revus/app/git_operations.py
revus/app/llm_client.py
revus/app/logger.py
revus/app/review_executor.py
revus/app/review_manager.py
revus/main.py
revus-0.0.2.dist-info/METADATA
revus-0.0.2.dist-info/WHEEL
revus-0.0.2.dist-info/entry_points.txt
revus-0.0.2.dist-info/RECORD
